alphadia_search_rs-1.1.1.dist-info/METADATA
alphadia_search_rs-1.1.1.dist-info/WHEEL
alphadia_search_rs-1.1.1.dist-info/licenses/LICENSE.txt
alphadia_search_rs/__init__.py
alphadia_search_rs/alphadia_search_rs.cp312-win_amd64.pyd
alphadia_search_rs-1.1.1.dist-info/RECORD
