Metadata-Version: 2.4
Name: alphadia-search-rs
Version: 1.1.1
Classifier: Development Status :: 4 - Beta
Classifier: Intended Audience :: Science/Research
Classifier: License :: OSI Approved :: Apache Software License
Classifier: Operating System :: OS Independent
Classifier: Programming Language :: Rust
Classifier: Programming Language :: Python :: Implementation :: CPython
Classifier: Programming Language :: Python :: Implementation :: PyPy
Classifier: Topic :: Scientific/Engineering :: Bio-Informatics
Requires-Dist: alphabase ; extra == 'dev'
Requires-Dist: pytest ; extra == 'dev'
Requires-Dist: numpy ; extra == 'dev'
Provides-Extra: dev
License-File: LICENSE.txt
Summary: A next-generation search backend for AlphaDIA.
Keywords: mass spectrometry,proteomics,search engine,DIA,data-independent acquisition,bioinformatics,AlphaPept,AlphaPept ecosystem,alphapept.org
Author-email: Mann Labs <wallmann@biochem.mpg.de>
Requires-Python: >=3.10
Project-URL: homepage, https://www.alphapept.org
Project-URL: Mann Labs Homepage, https://www.biochem.mpg.de/mann
